template/src/SimpleAndGate.vhdl
library ieee;
use ieee.std_logic_1164.all;


entity SimpleAndGate is
    port (
        A : in  std_logic;
        B : in  std_logic;
        O : out std_logic
    );
end entity;


architecture behavioral of SimpleAndGate is
begin
    O <= A and B;
end architecture;

template/src/AwesomeTripleAndGate.vhdl
library ieee;
use ieee.std_logic_1164.all;


entity AwesomeTripleAndGate is
    port (
        A : in  std_logic;
        B : in  std_logic;
        C : in  std_logic;
        O : out std_logic
    );
end entity;


architecture behavioral of AwesomeTripleAndGate is
    signal temp : std_logic;
begin
    AND0: entity work.SimpleAndGate(behavioral) port map (A, B, temp);
    AND1: entity work.SimpleAndGate(behavioral) port map (C, temp, O);
end architecture;

template/tb/AwesomeTripleAndGate_tb.vhd
library ieee;
use ieee.std_logic_1164.all;
use ieee.numeric_std.all;


entity AwesomeTripleAndGate_tb is
end entity;


architecture test of AwesomeTripleAndGate_tb is
    signal A : std_logic;
    signal B : std_logic;
    signal C : std_logic;
    signal O : std_logic;

    signal temp : std_logic_vector (2 downto 0) := "000";
begin
    T0: entity work.AwesomeTripleAndGate(behavioral) port map (A, B, C, O);

    test: process
    begin
        -- For inputs 000 through 110, output should be zero
        for i in 0 to 6 loop
            temp <= std_logic_vector(to_unsigned(i, 3));
            wait for 1 ns;
            
            A <= temp(0);
            B <= temp(1);
            C <= temp(2);

            wait for 1 ns;
            assert O = '0' report "Output is wrong for inputs other than 111" severity error;
        end loop;

        A <= '1';
        B <= '1';
        C <= '1';

        wait for 1 ns;
        assert O = '1' report "Output is wrong for input 111" severity error;
    end process;
end architecture;

template/simu/AwesomeTripleAndGate.vcd
$date
  Thu Oct 23 21:11:08 2025
$end
$version
  GHDL v0
$end
$timescale
  1 fs
$end
$scope module standard $end
$upscope $end
$scope module std_logic_1164 $end
$upscope $end
$scope module numeric_std $end
$upscope $end
$scope module awesometripleandgate_tb $end
$var reg 1 ! a $end
$var reg 1 " b $end
$var reg 1 # c $end
$var reg 1 $ o $end
$var reg 3 % temp[2:0] $end
$scope module t0 $end
$var reg 1 & a $end
$var reg 1 ' b $end
$var reg 1 ( c $end
$var reg 1 ) o $end
$var reg 1 * temp $end
$scope module and0 $end
$var reg 1 + a $end
$var reg 1 , b $end
$var reg 1 - o $end
$upscope $end
$scope module and1 $end
$var reg 1 . a $end
$var reg 1 / b $end
$var reg 1 0 o $end
$upscope $end
$upscope $end
$upscope $end
$enddefinitions $end
#0
U!
U"
U#
U$
b000 %
U&
U'
U(
U)
U*
U+
U,
U-
U.
U/
U0
#1000000
0!
0"
0#
0$
0&
0'
0(
0)
0*
0+
0,
0-
0.
0/
00
#2000000
b001 %
#3000000
1!
1&
1+
#4000000
b010 %
#5000000
0!
1"
0&
1'
0+
1,
#6000000
b011 %
#7000000
1!
1&
1*
1+
1-
1/
#8000000
b100 %
#9000000
0!
0"
1#
0$
0&
0'
1(
0)
0*
0+
0,
0-
1.
0/
00
#10000000
b101 %
#11000000
1!
1&
1+
#12000000
b110 %
#13000000
0!
1"
0&
1'
0+
1,
#14000000
1!
1$
1&
1)
1*
1+
1-
1/
10
#15000000
b000 %
#16000000
0!
0"
0#
0$
0&
0'
0(
0)
0*
0+
0,
0-
0.
0/
00
#17000000
b001 %
#18000000
1!
1&
1+
#19000000
b010 %
#20000000
0!
1"
0&
1'
0+
1,
#21000000
b011 %
#22000000
1!
1&
1*
1+
1-
1/
#23000000
b100 %
#24000000
0!
0"
1#
0$
0&
0'
1(
0)
0*
0+
0,
0-
1.
0/
00
#25000000
b101 %
#26000000
1!
1&
1+
#27000000
b110 %
#28000000
0!
1"
0&
1'
0+
1,
#29000000
1!
1$
1&
1)
1*
1+
1-
1/
10
#30000000
b000 %
#31000000
0!
0"
0#
0$
0&
0'
0(
0)
0*
0+
0,
0-
0.
0/
00
#32000000
b001 %
#33000000
1!
1&
1+
#34000000
b010 %
#35000000
0!
1"
0&
1'
0+
1,
#36000000
b011 %
#37000000
1!
1&
1*
1+
1-
1/
#38000000
b100 %
#39000000
0!
0"
1#
0$
0&
0'
1(
0)
0*
0+
0,
0-
1.
0/
00
#40000000
b101 %
#41000000
1!
1&
1+
#42000000
b110 %
#43000000
0!
1"
0&
1'
0+
1,
#44000000
1!
1$
1&
1)
1*
1+
1-
1/
10
#45000000
b000 %
#46000000
0!
0"
0#
0$
0&
0'
0(
0)
0*
0+
0,
0-
0.
0/
00
#47000000
b001 %
#48000000
1!
1&
1+
#49000000
b010 %
#50000000
0!
1"
0&
1'
0+
1,
#51000000
b011 %
#52000000
1!
1&
1*
1+
1-
1/
#53000000
b100 %
#54000000
0!
0"
1#
0$
0&
0'
1(
0)
0*
0+
0,
0-
1.
0/
00
#55000000
b101 %
#56000000
1!
1&
1+
#57000000
b110 %
#58000000
0!
1"
0&
1'
0+
1,
#59000000
1!
1$
1&
1)
1*
1+
1-
1/
10
#60000000
b000 %
#61000000
0!
0"
0#
0$
0&
0'
0(
0)
0*
0+
0,
0-
0.
0/
00
#62000000
b001 %
#63000000
1!
1&
1+
#64000000
b010 %
#65000000
0!
1"
0&
1'
0+
1,
#66000000
b011 %
#67000000
1!
1&
1*
1+
1-
1/
#68000000
b100 %
#69000000
0!
0"
1#
0$
0&
0'
1(
0)
0*
0+
0,
0-
1.
0/
00
#70000000
b101 %
#71000000
1!
1&
1+
#72000000
b110 %
#73000000
0!
1"
0&
1'
0+
1,
#74000000
1!
1$
1&
1)
1*
1+
1-
1/
10
#75000000
b000 %
#76000000
0!
0"
0#
0$
0&
0'
0(
0)
0*
0+
0,
0-
0.
0/
00
#77000000
b001 %
#78000000
1!
1&
1+
#79000000
b010 %
#80000000
0!
1"
0&
1'
0+
1,
#81000000
b011 %
#82000000
1!
1&
1*
1+
1-
1/
#83000000
b100 %
#84000000
0!
0"
1#
0$
0&
0'
1(
0)
0*
0+
0,
0-
1.
0/
00
#85000000
b101 %
#86000000
1!
1&
1+
#87000000
b110 %
#88000000
0!
1"
0&
1'
0+
1,
#89000000
1!
1$
1&
1)
1*
1+
1-
1/
10
#90000000
b000 %
#91000000
0!
0"
0#
0$
0&
0'
0(
0)
0*
0+
0,
0-
0.
0/
00
#92000000
b001 %
#93000000
1!
1&
1+
#94000000
b010 %
#95000000
0!
1"
0&
1'
0+
1,
#96000000
b011 %
#97000000
1!
1&
1*
1+
1-
1/
#98000000
b100 %
#99000000
0!
0"
1#
0$
0&
0'
1(
0)
0*
0+
0,
0-
1.
0/
00
#100000000
b101 %
